acdh_bible_pyutils/__init__.py
acdh_bible_pyutils/bible_books.csv
acdh_bible_pyutils-0.2.dist-info/METADATA
acdh_bible_pyutils-0.2.dist-info/WHEEL
acdh_bible_pyutils-0.2.dist-info/licenses/LICENSE
acdh_bible_pyutils-0.2.dist-info/RECORD
