Metadata-Version: 2.4
Name: acdh-bible-pyutils
Version: 0.2
Summary: Utility functions for dealing with biblicial references
Author-email: csae8092 <p.andorfer@gmail.com>
License-File: LICENSE
Requires-Python: >=3.12
